aio_periodic/__init__.py
aio_periodic/client.py
aio_periodic/job.py
aio_periodic/pool.py
aio_periodic/transport.py
aio_periodic/worker.py
aio_periodic/types/__init__.py
aio_periodic/types/agent.py
aio_periodic/types/base_client.py
aio_periodic/types/command.py
aio_periodic/types/job.py
aio_periodic/types/utils.py
aio_periodic-0.2.8.dist-info/METADATA
aio_periodic-0.2.8.dist-info/WHEEL
aio_periodic-0.2.8.dist-info/top_level.txt
aio_periodic-0.2.8.dist-info/RECORD
