Metadata-Version: 2.1
Name: aio-periodic
Version: 0.2.8
Summary: The periodic task system client for python3 base on asyncio
Home-page: https://github.com/Lupino/python-aio-periodic
Author: Li Meng Jun
Author-email: lmjubuntu@gmail.com
License: UNKNOWN
Platform: UNKNOWN
